{"auth_reset.md":"ViVBI8U5","meet-the-heisenberg_index.md":"FsD3JmcX","pixel-synth_index.md":"oqZajiio","cardboard-synth_index.md":"IBctjKTK","disco-computer_index.md":"DYqI7VFP","acid-machine-2_index.md":"TJ6gQ4yV","note-sculptor_index.md":"LeGI52So","aqwertyon_index.md":"VWtfEOBV","mod-synth_index.md":"kX7c_CUH","auth_logout.md":"WkIPn6Dn","sample-stich_index.md":"Z6Y8wGC8","sound-box_index.md":"sYj-2C_n","video-sampler_index.md":"enT_9Ye7","touch-pianist_index.md":"jAFZ9YS1","midi-driven-web-audio_index.md":"r_1tq2kq","websynths_index.md":"W8E2pYmK","ableton_index.md":"jo6qaowD","auth_accept.md":"1r0dQsQN","virtual-piano_index.md":"2sQgBRfl","web-sid_index.md":"KghNW4ke","sympathetic_index.md":"ys-2q3ab","auth.md":"-wuNXtSc","web-audio-synth-v2_index.md":"_ZDjHjT-","theremin_index.md":"7hUMqBQx","muted-io_index.md":"pjbwEGqy","dotpiano_index.md":"TYua1pj1","groove-pizza_index.md":"WIrAx9Fv","tanguy-synth_index.md":"qRwd5ZrY","auth_invite.md":"SfI6cbKj","auth_index.md":"P1vRL8YF","online-sequencer_index.md":"WoI80hXu","omni_index.md":"zinhJV2q","waveform_index.md":"h9NxgJPt","web-modular_index.md":"e_w7uO7K","elementary_index.md":"FFI2VnYk","dx7_index.md":"kGwZEoD4","touchme_index.md":"j144GAOl","olif-sy-1-k_index.md":"JTosYTlz","index.md":"b2_Q5YQj","nv-1_index.md":"AgoqbZEv","readme.md":"vIrSkC-V","sound-trap_index.md":"ur_TH-LP","sampler_index.md":"c56ALYEH","juno-106_index.md":"UHBLh480"}
